Metadata-Version: 2.1
Name: tox-docker
Version: 5.0.0
Summary: Manage lifecycle of docker containers during Tox test runs
Home-page: https://github.com/tox-dev/tox-docker
Maintainer: Dan Crosta
Maintainer-email: dcrosta@late.am
Classifier: Development Status :: 5 - Production/Stable
Classifier: Environment :: Plugins
Classifier: Intended Audience :: Developers
Classifier: License :: OSI Approved :: BSD License
Classifier: Programming Language :: Python :: 3.8
Classifier: Programming Language :: Python :: 3.9
Classifier: Programming Language :: Python :: 3.10
Classifier: Programming Language :: Python :: 3.11
Classifier: Topic :: Software Development :: Testing
License-File: LICENSE
Requires-Dist: docker <8.0,>=4.0
Requires-Dist: tox <5.0,>=4.0.0
